UnityBuildPipeline-0.0.8.1.data/scripts/pipeline
unity_build_pipeline/__init__.py
unity_build_pipeline/Modes/__init__.py
unity_build_pipeline/Modes/modes_base/__init__.py
unity_build_pipeline/Modes/modes_base/base_modes.py
unity_build_pipeline/Modes/modes_base/command.py
unity_build_pipeline/Modes/modes_base/root_mode.py
unity_build_pipeline/Modes/pipeline_modes/CleanMode.py
unity_build_pipeline/Modes/pipeline_modes/ExampleMode.py
unity_build_pipeline/Modes/pipeline_modes/ExportMode.py
unity_build_pipeline/Modes/pipeline_modes/FastlaneMode.py
unity_build_pipeline/Modes/pipeline_modes/InitMode.py
unity_build_pipeline/Modes/pipeline_modes/RapidMode.py
unity_build_pipeline/Modes/pipeline_modes/RunMode.py
unity_build_pipeline/Modes/pipeline_modes/__init__.py
unity_build_pipeline/Services/Fastlane.py
unity_build_pipeline/Services/Project.py
unity_build_pipeline/Services/Unity.py
unity_build_pipeline/Services/__init__.py
unity_build_pipeline/Services/config/Config.py
unity_build_pipeline/Services/config/__init__.py
unity_build_pipeline/Support/__init__.py
unity_build_pipeline/Support/config.py
unity_build_pipeline/Support/fileutils.py
unity_build_pipeline/Support/logger.py
unity_build_pipeline/Support/shell.py
unity_build_pipeline/stubs/.DS_Store
unity_build_pipeline/stubs/Fastlane/Gemfile
unity_build_pipeline/stubs/Fastlane/fastlane/Appfile
unity_build_pipeline/stubs/Fastlane/fastlane/Fastfile
unity_build_pipeline/stubs/Unity/IOSExportTool.cs.stub
UnityBuildPipeline-0.0.8.1.dist-info/METADATA
UnityBuildPipeline-0.0.8.1.dist-info/WHEEL
UnityBuildPipeline-0.0.8.1.dist-info/top_level.txt
UnityBuildPipeline-0.0.8.1.dist-info/RECORD
