Metadata-Version: 2.1
Name: UnityBuildPipeline
Version: 0.0.8.1
Summary: Unity build pipeline for iOS
Home-page: https://github.com/MadCoder39/UnityBuildPipelineiOS
Author: MadCoder
Author-email: madcoder39@gmail.com
License: UNKNOWN
Platform: UNKNOWN
Classifier: Programming Language :: Python :: 3
Classifier: License :: OSI Approved :: MIT License
Classifier: Operating System :: MacOS
Requires-Dist: pyyaml
